Workbook

Sheet LEIA
A1: MEMÓRIA DE CÁLCULO – BLOCO 08 (PT 530 e parte simulada do PT 450) – base SINTÉTICA, cenário TESTE – não são dados da ISA Energia Brasil
A2: Células amarelas = entradas (parâmetros do desenho congelado ou resultados do b08_testes.py). Demais = fórmulas. Valores em R$.
A3: Fator de confiança: GAMMAINV(0,95; k+1; 1) = limite superior de Poisson para k distorções (equivale à tabela usual de MUS).
A4: Sem uso do gabarito: esta planilha foi gerada antes do confronto (controle/CONGELAMENTO_RESULTADOS.json).
A5: Preparado por: matrícula 241003689 (execução assistida por IA). Revisão humana: ____________ (em branco).

Sheet Dimensionamento_MUS
A1: Parâmetro | B1: Valor | C1: Fonte / natureza
A2: Materialidade de execução – ME (R$) | B2: 90000000 | C2: D-014 – exigência: TM ≤ ME (530 A3)
A3: Σ |efeito no saldo| – Estágio 1 (R$) | B3: 44928821 | C3: Resultado b08_testes.py
A4: Σ |efeito no resultado| – Estágio 1 (R$) | B4: 48456342 | C4: Resultado b08_testes.py
A5: TM da amostra (R$) = ME − máx | B5: =B2-MAX(B3,B4) -> 41543658 | C5: Regra do desenho (julgamento conservador: distorções presumidas não corrigidas)
A6: Erro esperado – EE (R$) | B6: 9000000 | C6: Premissa didática (B06; 10% da ME) – julgamento
A7: Fator de expansão – FE | B7: 1.6 | C7: Tabela usual de MUS, 5% de risco – julgamento
A8: Confiança | B8: 0.95 | C8: Risco significativo, controles não testados (PT 330) – julgamento
A9: Fator de confiança 0 erros – FC(0) | B9: =GAMMAINV(B8,1,1) -> 2.9957323 | C9: Poisson: −ln(0,05)
A10: Valor contábil do restante – VC (R$) | B10: 6.4242859e+09 | C10: População TD-01 − itens específicos − estrato superior
A11: Tamanho n = ⌈VC × FC / (TM − EE × FE)⌉ | B11: =ROUNDUP(B10*B9/(B5-B6*B7),0) -> 710 | C11: 530 it. 7; A11 (fórmula estatística)
A12: Intervalo J (R$) = ⌊VC / n⌋ | B12: =ROUNDDOWN(B10*100/B11,0)/100 -> 9048290.1 | C12: Itens ≥ J vão para o estrato superior (100%)
A13: Início aleatório (centavos) | B13: 519156127 | C13: Semente 2025123108 (numpy PCG64)
A14: n efetivamente selecionado (código) | B14: 710 | C14: AMOSTRA_MUS.csv
A15: Conferência: n fórmula − n código | B15: =B11-B14 -> 0 | C15: Deve ser 0
A16: Referência B06 (sem Estágio 1; VC total; TM = ME) | B16: 257 | C16: Comparação – tamanho maior agora porque o TM foi reduzido pelas distorções já encontradas

Sheet Avaliacao_MUS
A1: Item | B1: Valor | C1: Fórmula / nota
A2: J (R$) | B2: =Dimensionamento_MUS!B12 -> 9048290.1
A3: Confiança | B3: =Dimensionamento_MUS!B8 -> 0.95
A4: Itens na amostra | B4: 710
A5: Itens com distorção na amostra | B5: 0
A6: Soma das distorções detectadas na amostra (R$) | B6: 0 | C6: Valor real encontrado – NÃO é a projeção
A7: Precisão básica = FC(0) × J | B7: =GAMMAINV(B3,1,1)*B2 -> 27106255 | C7: Risco de amostragem com 0 distorções
A8: Distorção projetada = Σ t × J | B8: 0 | C8: 530 it. 14; A18
A9: Acréscimo por distorções ordenadas | B9: 0 | C9: Σ t(i) × (FC(i) − FC(i−1) − 1)
A10: LIMITE SUPERIOR de distorção (restante) | B10: =B7+B8+B9 -> 27106255 | C10: Limite de avaliação (inclui risco de amostragem)
A11: TM da amostra | B11: =Dimensionamento_MUS!B5 -> 41543658
A12: Folga = TM − limite superior | B12: =B11-B10 -> 14437403 | C12: > 0: amostra dá base razoável (530 A22)
A13: Estrato superior: itens / valor / distorção real (R$) | B13: 1 / 10,000,000.00 / 0.00 | C13: Examinado a 100%; sem projeção
A19: Contaminações ordenadas (t) e incremento de fator
A20: Nenhuma distorção na amostra: distorção projetada = 0; limite superior = precisão básica.

Sheet Estagio1_distorcoes
A1: Teste | regra | B1: Linhas | C1: Efeito no saldo 31/12/2025 (R$) | D1: Efeito no resultado 2025 (R$) | E1: Natureza (450 A6) | F1: Meio de seleção
A2: TD-01|R1 | B2: 35 | C2: 4893510.1 | D2: 4893510.1 | E2: Factual | F2: 100% / itens específicos (não é amostragem; sem projeção – 500 A66)
A3: TD-01|R2 | B3: 20 | C3: 7716140.9 | D3: 7716140.9 | E3: Factual | F3: 100% / itens específicos (não é amostragem; sem projeção – 500 A66)
A4: TD-01|R4 | B4: 60 | C4: 4600000 | D4: 4600000 | E4: Factual | F4: 100% / itens específicos (não é amostragem; sem projeção – 500 A66)
A5: TD-01|R5 | B5: 150 | C5: 0 | D5: 3527521.1 | E5: Factual (corte; afeta abertura) | F5: 100% / itens específicos (não é amostragem; sem projeção – 500 A66)
A6: TD-01|R6 | B6: 2 | C6: 15500000 | D6: 15500000 | E6: Factual (sem suporte; indício de fraude) | F6: 100% / itens específicos (não é amostragem; sem projeção – 500 A66)
A7: TD-03|CORTE-2026 | B7: 273 | C7: -7201518.3 | D7: -7201518.3 | E7: Factual (subavaliação) | F7: 100% / itens específicos (não é amostragem; sem projeção – 500 A66)
A8: TD-05|REM | B8: 3 | C8: 5017651.7 | D8: 5017651.7 | E8: Factual (cálculo) | F8: 100% / itens específicos (não é amostragem; sem projeção – 500 A66)
A9: Total líquido | B9: =SUM(B2:B8) -> 543 | C9: =SUM(C2:C8) -> 30525784 | D9: =SUM(D2:D8) -> 34053306
A10: Total |absoluto| | C10: =SUMPRODUCT(ABS(C2:C8)) -> 44928821 | D10: =SUMPRODUCT(ABS(D2:D8)) -> 48456342
A12: Classificação (sem efeito no total): TD-04 recebimentos aplicados a outro contrato (R$) | C12: -1986044.8

Sheet Agregacao_PT450
A1: Componente | B1: Saldo 31/12/2025 (R$) | C1: Resultado 2025 (R$) | D1: Nota
A2: (1) Distorções factuais identificadas – líquido | B2: =Estagio1_distorcoes!C9 -> 30525784 | C2: =Estagio1_distorcoes!D9 -> 34053306 | D2: 100%/itens específicos; sem risco de amostragem
A3: (2) Distorções de julgamento | B3: 0 | C3: 0 | D3: TD-06: exceção explicada por evidência pública (F0003 p.37, 46); nenhuma registrada
A4: (3) Distorção projetada (MUS, restante) | B4: =Avaliacao_MUS!B8 -> 0 | C4: =Avaliacao_MUS!B8 -> 0 | D4: Superavaliação de débitos de receita/ativo
A5: (4) Melhor estimativa = (1)+(2)+(3) | B5: =B2+B3+B4 -> 30525784 | C5: =C2+C3+C4 -> 34053306 | D5: 450 A6; 530 A22
A6: (5) Margem para risco de amostragem = limite superior − projetada | B6: =Avaliacao_MUS!B10-Avaliacao_MUS!B8 -> 27106255 | C6: =Avaliacao_MUS!B10-Avaliacao_MUS!B8 -> 27106255 | D6: Não é distorção identificada
A7: (6) Limite superior agregado = (4)+(5) | B7: =B5+B6 -> 57632039 | C7: =C5+C6 -> 61159560 | D7: Comparar com ME e MG
A8: ME | B8: 90000000 | C8: 90000000 | D8: D-014
A9: MG | B9: 139000000 | C9: 139000000 | D9: D-014
A10: CT | B10: 7000000 | C10: 7000000 | D10: D-014
A11: (6) / ME | B11: =B7/B8 -> 0.64035599 | C11: =C7/C8 -> 0.67955067
A12: Conciliação: TESTE − publicado (PT 500, C1) | B12: 31725784 | D12: CONCILIACAO_BASE_B07 aba C_TESTE
A13: Explicado pelas distorções factuais líquidas (saldo) | B13: =B2 -> 30525784
A14: Diferença de conciliação NÃO explicada | B14: =ROUND(B12-B13,2) -> 1200000 | D14: Localizada em O&M / perda esperada (C2 e C4 do C_TESTE): a investigar no PT 540

Sheet TD05_remuneracao
A1: Contrato | B1: Comp. | C1: Competência | D1: Base (R$) | E1: Valor (R$) | F1: Taxa | G1: Taxa modal | H1: Fator modal | I1: Esperado = base × fator | J1: Diferença
A2: 001/2008 | B2: IMPL | C2: 2025-01 | D2: 6.1754228e+08 | E2: 6699872.3 | F2: 0.0873 | G2: 0.0873 | H2: 0.010849253 | I2: =ROUND(D2*H2,2) -> 6699872.3 | J2: =ROUND(E2-I2,2) -> -0.03
A3: 001/2008 | B3: IMPL | C3: 2025-02 | D3: 6.180728e+08 | E3: 6705628 | F3: 0.0873 | G3: 0.0873 | H3: 0.010849253 | I3: =ROUND(D3*H3,2) -> 6705628.1 | J3: =ROUND(E3-I3,2) -> -0.03
A4: 001/2008 | B4: IMPL | C4: 2025-03 | D4: 6.1828977e+08 | E4: 6707982 | F4: 0.0873 | G4: 0.0873 | H4: 0.010849253 | I4: =ROUND(D4*H4,2) -> 6707982 | J4: =ROUND(E4-I4,2) -> -0.02
A5: 001/2008 | B5: IMPL | C5: 2025-04 | D5: 6.187586e+08 | E5: 6713068.4 | F5: 0.0873 | G5: 0.0873 | H5: 0.010849253 | I5: =ROUND(D5*H5,2) -> 6713068.5 | J5: =ROUND(E5-I5,2) -> -0.03
A6: 001/2008 | B6: IMPL | C6: 2025-05 | D6: 6.1918536e+08 | E6: 6717698.5 | F6: 0.0873 | G6: 0.0873 | H6: 0.010849253 | I6: =ROUND(D6*H6,2) -> 6717698.5 | J6: =ROUND(E6-I6,2) -> -0.03
A7: 001/2008 | B7: IMPL | C7: 2025-06 | D7: 6.1953385e+08 | E7: 6721479.4 | F7: 0.0873 | G7: 0.0873 | H7: 0.010849253 | I7: =ROUND(D7*H7,2) -> 6721479.4 | J7: =ROUND(E7-I7,2) -> -0.03
A8: 001/2008 | B8: IMPL | C8: 2025-07 | D8: 6.1991679e+08 | E8: 6725634 | F8: 0.0873 | G8: 0.0873 | H8: 0.010849253 | I8: =ROUND(D8*H8,2) -> 6725634 | J8: =ROUND(E8-I8,2) -> -0.03
A9: 001/2008 | B9: IMPL | C9: 2025-08 | D9: 6.2018313e+08 | E9: 6728523.6 | F9: 0.0873 | G9: 0.0873 | H9: 0.010849253 | I9: =ROUND(D9*H9,2) -> 6728523.6 | J9: =ROUND(E9-I9,2) -> -0.02
A10: 001/2008 | B10: IMPL | C10: 2025-09 | D10: 6.205405e+08 | E10: 6732400.8 | F10: 0.0873 | G10: 0.0873 | H10: 0.010849253 | I10: =ROUND(D10*H10,2) -> 6732400.8 | J10: =ROUND(E10-I10,2) -> -0.03
A11: 001/2008 | B11: IMPL | C11: 2025-10 | D11: 6.2149166e+08 | E11: 6742720.2 | F11: 0.0873 | G11: 0.0873 | H11: 0.010849253 | I11: =ROUND(D11*H11,2) -> 6742720.2 | J11: =ROUND(E11-I11,2) -> -0.03
A12: 001/2008 | B12: IMPL | C12: 2025-11 | D12: 6.2241195e+08 | E12: 6752704.6 | F12: 0.0873 | G12: 0.0873 | H12: 0.010849253 | I12: =ROUND(D12*H12,2) -> 6752704.6 | J12: =ROUND(E12-I12,2) -> -0.02
A13: 001/2008 | B13: IMPL | C13: 2025-12 | D13: 6.2284661e+08 | E13: 6757420.2 | F13: 0.0873 | G13: 0.0873 | H13: 0.010849253 | I13: =ROUND(D13*H13,2) -> 6757420.3 | J13: =ROUND(E13-I13,2) -> -0.02
... A337: 143/2001 | B337: IMPL | C337: 2025-12 | D337: 1.7795179e+08 | E337: 1704525.4 | F337: 0.0715 | G337: 0.0715 | H337: 0.0095785797 | I337: =ROUND(D337*H337,2) -> 1704525.4 | J337: =ROUND(E337-I337,2) -> 0
A338: Σ |diferenças| > R$ 1 | J338: =SUMPRODUCT((ABS(J2:J337)>1)*J2:J337) -> 5017651.7

Sheet TD06_classificacao
A1: Contrato | B1: Comp. | C1: Índice 2024 | D1: Índice 2025 | E1: Circulante 2025 | F1: Esperado (índice 2024) | G1: Diferença | H1: Variação p.p. | I1: Exceção pela regra
A2: 001/2008 | B2: IMPL | C2: 0.077506626 | D2: 0.08728129 | E2: 56508508 | F2: 50180099 | G2: =E2-F2 -> 6328408.9 | H2: =(D2-C2)*100 -> 0.97746642 | I2: =IF(OR(AND(B2="OEM",ABS(D2-1)>0.000001),AND(ABS(H2)>10,ABS(G2)>=7000000)),"SIM","não") -> não
A3: 001/2008 | B3: OEM | C3: 1 | D3: 1 | E3: 5214887.4 | F3: 5214887.4 | G3: =E3-F3 -> 0 | H3: =(D3-C3)*100 -> 0 | I3: =IF(OR(AND(B3="OEM",ABS(D3-1)>0.000001),AND(ABS(H3)>10,ABS(G3)>=7000000)),"SIM","não") -> não
A4: 001/2020 | B4: IMPL | C4: 0.077506626 | D4: 0.080953673 | E4: 44528482 | F4: 42632437 | G4: =E4-F4 -> 1896044.6 | H4: =(D4-C4)*100 -> 0.3447047 | I4: =IF(OR(AND(B4="OEM",ABS(D4-1)>0.000001),AND(ABS(H4)>10,ABS(G4)>=7000000)),"SIM","não") -> não
A5: 001/2020 | B5: OEM | C5: 1 | D5: 1 | E5: 4109310.7 | F5: 4109310.7 | G5: =E5-F5 -> 0 | H5: =(D5-C5)*100 -> 0 | I5: =IF(OR(AND(B5="OEM",ABS(D5-1)>0.000001),AND(ABS(H5)>10,ABS(G5)>=7000000)),"SIM","não") -> não
A6: 004/2007 | B6: IMPL | C6: 0.077506626 | D6: 0.089052245 | E6: 14602577 | F6: 12709354 | G6: =E6-F6 -> 1893223.4 | H6: =(D6-C6)*100 -> 1.1545619 | I6: =IF(OR(AND(B6="OEM",ABS(D6-1)>0.000001),AND(ABS(H6)>10,ABS(G6)>=7000000)),"SIM","não") -> não
A7: 004/2007 | B7: OEM | C7: 1 | D7: 1 | E7: 1347598.7 | F7: 1347598.7 | G7: =E7-F7 -> 0 | H7: =(D7-C7)*100 -> 0 | I7: =IF(OR(AND(B7="OEM",ABS(D7-1)>0.000001),AND(ABS(H7)>10,ABS(G7)>=7000000)),"SIM","não") -> não
A8: 005/2021 | B8: IMPL | C8: 0.067818298 | D8: 0.056015156 | E8: 44478043 | F8: 53850161 | G8: =E8-F8 -> -9372117.9 | H8: =(D8-C8)*100 -> -1.1803142 | I8: =IF(OR(AND(B8="OEM",ABS(D8-1)>0.000001),AND(ABS(H8)>10,ABS(G8)>=7000000)),"SIM","não") -> não
A9: 005/2021 | B9: OEM | C9: 0 | D9: 1 | E9: 6477607.9 | F9: 0 | G9: =E9-F9 -> 6477607.9 | H9: =(D9-C9)*100 -> 100 | I9: =IF(OR(AND(B9="OEM",ABS(D9-1)>0.000001),AND(ABS(H9)>10,ABS(G9)>=7000000)),"SIM","não") -> não
A10: 006/2020 | B10: IMPL | C10: 0.077506626 | D10: 0.059484852 | E10: 5897871.8 | F10: 7684715.2 | G10: =E10-F10 -> -1786843.4 | H10: =(D10-C10)*100 -> -1.8021774 | I10: =IF(OR(AND(B10="OEM",ABS(D10-1)>0.000001),AND(ABS(H10)>10,ABS(G10)>=7000000)),"SIM","não") -> não
A11: 006/2020 | B11: OEM | C11: 1 | D11: 1 | E11: 544285.07 | F11: 544285.07 | G11: =E11-F11 -> 0 | H11: =(D11-C11)*100 -> 0 | I11: =IF(OR(AND(B11="OEM",ABS(D11-1)>0.000001),AND(ABS(H11)>10,ABS(G11)>=7000000)),"SIM","não") -> não
A12: 006/2023 | B12: IMPL | C12: 1.1111111e-11 | D12: 4.2621244e-12 | E12: 0.01 | F12: 0.03 | G12: =E12-F12 -> -0.02 | H12: =(D12-C12)*100 -> -6.8489867e-10 | I12: =IF(OR(AND(B12="OEM",ABS(D12-1)>0.000001),AND(ABS(H12)>10,ABS(G12)>=7000000)),"SIM","não") -> não
A13: 007/2020 | B13: IMPL | C13: 0.077506626 | D13: 0.078570608 | E13: 36370892 | F13: 35878367 | G13: =E13-F13 -> 492524.82 | H13: =(D13-C13)*100 -> 0.1063982 | I13: =IF(OR(AND(B13="OEM",ABS(D13-1)>0.000001),AND(ABS(H13)>10,ABS(G13)>=7000000)),"SIM","não") -> não
... A56: 143/2001 | B56: OEM | C56: 1 | D56: 1 | E56: 1503832.2 | F56: 1503832.2 | G56: =E56-F56 -> 0 | H56: =(D56-C56)*100 -> 0 | I56: =IF(OR(AND(B56="OEM",ABS(D56-1)>0.000001),AND(ABS(H56)>10,ABS(G56)>=7000000)),"SIM","não") -> não
