Workbook

Sheet Mapa_grupo
A1: Mapa do grupo ISA Energia Brasil em 31/12/2025 (posição; eventos de 2026 separados). Fontes: F0003 p.40–41 (nota 2.5), p.58 (nota 6.5), p.59–62 (nota 7).
A3: Entidade | B3: Tipo em 31/12/2025 | C3: Participação ISA | D3: Método nas DFs consolidadas | E3: Método nas DFs individuais | F3: Data-base | G3: Fundamento da classificação | H3: Fonte | I3: Evento posterior (2026) – não altera 31/12/2025
A4: ISA Energia Brasil S.A. | B4: Controladora (entidade que reporta) | C4: — | D4: Base do consolidado | E4: — | F4: 31/12/2025 | G4: — | H4: F0003 p.38–40
A5: IE Serra do Japi | B5: Controlada | C5: 1 | D5: Consolidação integral | E5: Equivalência patrimonial | F5: 31/12/2025 | G5: Participação de 100% (controle – CPC 36/IFRS 10) | H5: F0003 p.40; F0268
A6: IEMG | B6: Controlada | C6: 1 | D6: Consolidação integral | E6: Equivalência patrimonial | F6: 31/12/2025 | G6: Participação de 100% (controle – CPC 36/IFRS 10) | H6: F0003 p.40; F0263
A7: IENNE | B7: Controlada | C7: 1 | D7: Consolidação integral | E7: Equivalência patrimonial | F7: 31/12/2025 | G7: Participação de 100% (controle – CPC 36/IFRS 10) | H7: F0003 p.40; F0264
A8: IE Pinheiros | B8: Controlada | C8: 1 | D8: Consolidação integral | E8: Equivalência patrimonial | F8: 31/12/2025 | G8: Participação de 100% (controle – CPC 36/IFRS 10) | H8: F0003 p.40; F0267
A9: Evrecy | B9: Controlada | C9: 1 | D9: Consolidação integral | E9: Equivalência patrimonial | F9: 31/12/2025 | G9: Participação de 100% (controle – CPC 36/IFRS 10) | H9: F0003 p.40; F0262
A10: IE Itaúnas | B10: Controlada | C10: 1 | D10: Consolidação integral | E10: Equivalência patrimonial | F10: 31/12/2025 | G10: Participação de 100% (controle – CPC 36/IFRS 10) | H10: F0003 p.40; F0265
A11: IE Tibagi | B11: Controlada | C11: 1 | D11: Consolidação integral | E11: Equivalência patrimonial | F11: 31/12/2025 | G11: Participação de 100% (controle – CPC 36/IFRS 10) | H11: F0003 p.40; F0269
A12: IE Itaquerê | B12: Controlada | C12: 1 | D12: Consolidação integral | E12: Equivalência patrimonial | F12: 31/12/2025 | G12: Participação de 100% (controle – CPC 36/IFRS 10) | H12: F0003 p.40; F0271
A13: IE Itapura | B13: Controlada | C13: 1 | D13: Consolidação integral | E13: Equivalência patrimonial | F13: 31/12/2025 | G13: Participação de 100% (controle – CPC 36/IFRS 10) | H13: F0003 p.40; F0276
A14: IE Aguapeí | B14: Controlada | C14: 1 | D14: Consolidação integral | E14: Equivalência patrimonial | F14: 31/12/2025 | G14: Participação de 100% (controle – CPC 36/IFRS 10) | H14: F0003 p.40; F0261
A15: IESul | B15: Controlada | C15: 1 | D15: Consolidação integral | E15: Equivalência patrimonial | F15: 31/12/2025 | G15: Participação de 100% (controle – CPC 36/IFRS 10) | H15: F0003 p.40; F0270
A16: IE Biguaçu | B16: Controlada | C16: 1 | D16: Consolidação integral | E16: Equivalência patrimonial | F16: 31/12/2025 | G16: Participação de 100% (controle – CPC 36/IFRS 10) | H16: F0003 p.40; F0260
... A24: Fundo de Investimento Barra Bonita RF Ref. DI LP (adm. Banco do Brasil) | B24: Fundo exclusivo consolidado (controlado) | C24: 1 | D24: Consolidação integral, com participação de não controladores (R$ 285.544 mil) | E24: Aplicação financeira | F24: 31/12/2025 | G24: Participação direta e indireta; quotas restantes das controladas em conjunto viram não controladores; alterações de regulamento aprovadas pela ISA | H24: F0003 p.40 e p.58
A25: IE Madeira | B25: Controlada em conjunto (negócio em conjunto – joint venture) | C25: 0.51 | D25: Equivalência patrimonial | E25: Equivalência patrimonial | F25: 31/12/2025 | G25: Acordo de Acionistas de 18/12/2008 prevê controle em conjunto (F0259 p.17). Participação de 51% NÃO implica controle: há controle conjunto contratual | H25: F0003 p.41, p.61; F0259 | I25: CCVA de 19/03/2026 (F0102) e conclusão em 31/07/2026 (F0121): ISA passa a 100% e consolida a partir de ago/2026
A26: IE Garanhuns | B26: Controlada em conjunto (negócio em conjunto – joint venture) | C26: 0.51 | D26: Equivalência patrimonial | E26: Equivalência patrimonial | F26: 31/12/2025 | G26: CA com metade indicada por cada acionista (51%/49%) (F0258 p.5). Participação de 51% NÃO implica controle: há controle conjunto contratual | H26: F0003 p.41, p.61; F0258 | I26: Alienação dos 51% à Axia Nordeste concluída em 31/07/2026 (F0102, F0121); deixa a equivalência a partir de ago/2026
A27: IE Paraguaçu | B27: Controlada em conjunto (negócio em conjunto – joint venture) | C27: 0.5 | D27: Equivalência patrimonial | E27: Equivalência patrimonial | F27: 31/12/2025 | G27: Controle compartilhado por Acordo de Acionistas (Taesa 50%) (F0279 p.3). Participação de 51% NÃO implica controle: há controle conjunto contratual | H27: F0003 p.41, p.61; F0279
A28: IE Aimorés | B28: Controlada em conjunto (negócio em conjunto – joint venture) | C28: 0.5 | D28: Equivalência patrimonial | E28: Equivalência patrimonial | F28: 31/12/2025 | G28: Controle compartilhado por Acordo de Acionistas (Taesa 50%) (F0278 p.3). Participação de 51% NÃO implica controle: há controle conjunto contratual | H28: F0003 p.41, p.61; F0278
A29: IE Ivaí | B29: Controlada em conjunto (negócio em conjunto – joint venture) | C29: 0.5 | D29: Equivalência patrimonial | E29: Equivalência patrimonial | F29: 31/12/2025 | G29: "controlada em conjunto" pela ISA e Taesa (F0266, nota 1). Participação de 51% NÃO implica controle: há controle conjunto contratual | H29: F0003 p.41, p.61; F0266
A30: Coligadas | B30: Nenhuma identificada | C30: — | D30: — | E30: — | F30: — | G30: A nota 2.5/7 lista só controladas e controladas em conjunto; termo "coligada" aparece 2 vezes no F0003, sem investida desse tipo | H30: F0003 p.40–41, p.59–62
A31: Operações em conjunto (IFRS 11) | B31: Nenhuma identificada | C31: — | D31: — | E31: — | F31: — | G31: Não divulgada nas notas lidas | H31: F0003 nota 2.5

Sheet Matriz_componentes
A1: Matriz de componentes (R$ mil). Métricas extraídas das DFs 2025 de cada componente (página indicada). Conferência: lucro × participação = equivalência da nota 7 (F0003 p.60–61).
A2: Consolidado: ativo total 47.201.372; receita 9.411.153; LAIR 2.780.309 (F0003 p.23–25). ME do grupo 90.000; CT 7.000 (D-014).
A3: Componente | B3: Tipo | C3: ID | D3: Auditor (relatório público) | E3: Data do relatório do componente | F3: Opinião | G3: Ativo total 2025 | H3: Pág. ativo | I3: Receita líquida 2025 | J3: Lucro líquido 2025 | K3: Participação | L3: Equivalência nota 7 (2025) | M3: Diferença (lucro × part. − equiv.) | N3: Ativo total / ativo consolidado | O3: Investimento ISA (nota 7.2) | P3: Ativo da concessão 2025 (DF do componente) | Q3: Abordagem proposta (PT 600 §6.3)
A4: IE Serra do Japi | B4: Controlada | C4: F0268 | D4: Deloitte Touche Tohmatsu | E4: 31 de março de 2026 | F4: Sem modificação | G4: 509292 | H4: 5 | I4: 67237 | J4: 55783 | K4: 1 | L4: 55783 | M4: =ROUND(J4*K4-L4,0) -> 0 | N4: =G4/47201372 -> 0.010789771 | O4: 455479 | P4: 502167 | Q4: Centralizada (ativo contratual testado como população única – base sintética)
A5: IEMG | B5: Controlada | C5: F0263 | D5: Deloitte Touche Tohmatsu | E5: 31 de março de 2026 | F5: Sem modificação | G5: 668876 | H5: 5 | I5: 99341 | J5: 53422 | K5: 1 | L5: 53422 | M5: =ROUND(J5*K5-L5,0) -> 0 | N5: =G5/47201372 -> 0.01417069 | O5: 582077 | P5: 659147 | Q5: Centralizada (ativo contratual testado como população única – base sintética)
A6: IENNE | B6: Controlada | C6: F0264 | D6: Deloitte Touche Tohmatsu | E6: 31 de março de 2026 | F6: Sem modificação | G6: 585143 | H6: 5 | I6: 67719 | J6: 44933 | K6: 1 | L6: 44932 | M6: =ROUND(J6*K6-L6,0) -> 1 | N6: =G6/47201372 -> 0.012396737 | O6: 453448 | P6: 550466 | Q6: Centralizada (ativo contratual testado como população única – base sintética)
A7: IE Pinheiros | B7: Controlada | C7: F0267 | D7: Deloitte Touche Tohmatsu | E7: 31 de março de 2026 | F7: Sem modificação | G7: 80193 | H7: 5 | I7: 9653 | J7: 6908 | K7: 1 | L7: 6908 | M7: =ROUND(J7*K7-L7,0) -> 0 | N7: =G7/47201372 -> 0.0016989549 | O7: 70321 | P7: 67329 | Q7: Centralizada (ativo contratual testado como população única – base sintética)
A8: Evrecy | B8: Controlada | C8: F0262 | D8: Deloitte Touche Tohmatsu | E8: 31 de março de 2026 | F8: Sem modificação | G8: 706683 | H8: 5 | I8: 70842 | J8: 50861 | K8: 1 | L8: 50861 | M8: =ROUND(J8*K8-L8,0) -> 0 | N8: =G8/47201372 -> 0.014971662 | O8: 629464 | P8: 629579 | Q8: Centralizada (ativo contratual testado como população única – base sintética)
A9: IE Itaúnas | B9: Controlada | C9: F0265 | D9: Deloitte Touche Tohmatsu | E9: 31 de março de 2026 | F9: Sem modificação | G9: 690024 | H9: 5 | I9: 84693 | J9: 75705 | K9: 1 | L9: 75705 | M9: =ROUND(J9*K9-L9,0) -> 0 | N9: =G9/47201372 -> 0.014618728 | O9: 591221 | P9: 659875 | Q9: Centralizada (ativo contratual testado como população única – base sintética)
A10: IE Tibagi | B10: Controlada | C10: F0269 | D10: Deloitte Touche Tohmatsu | E10: 31 de março de 2026 | F10: Sem modificação | G10: 409544 | H10: 5 | I10: 103502 | J10: 43537 | K10: 1 | L10: 43538 | M10: =ROUND(J10*K10-L10,0) -> -1 | N10: =G10/47201372 -> 0.0086765275 | O10: 367497 | P10: 400587 | Q10: Centralizada (ativo contratual testado como população única – base sintética)
A11: IE Itaquerê | B11: Controlada | C11: F0271 | D11: Deloitte Touche Tohmatsu | E11: 31 de março de 2026 | F11: Sem modificação | G11: 695376 | H11: 5 | I11: 81685 | J11: 74853 | K11: 1 | L11: 74853 | M11: =ROUND(J11*K11-L11,0) -> 0 | N11: =G11/47201372 -> 0.014732114 | O11: 629364 | P11: 683902 | Q11: Centralizada (ativo contratual testado como população única – base sintética)
A12: IE Itapura | B12: Controlada | C12: F0276 | D12: Deloitte Touche Tohmatsu | E12: 31 de março de 2026 | F12: Sem modificação | G12: 228813 | H12: 5 | I12: 29783 | J12: 26368 | K12: 1 | L12: 26368 | M12: =ROUND(J12*K12-L12,0) -> 0 | N12: =G12/47201372 -> 0.0048475921 | O12: 205855 | P12: 223075 | Q12: Centralizada (ativo contratual testado como população única – base sintética)
A13: IE Aguapeí | B13: Controlada | C13: F0261 | D13: Deloitte Touche Tohmatsu | E13: 31 de março de 2026 | F13: Sem modificação | G13: 855504 | H13: 5 | I13: 103165 | J13: 81140 | K13: 1 | L13: 81140 | M13: =ROUND(J13*K13-L13,0) -> 0 | N13: =G13/47201372 -> 0.018124558 | O13: 603892 | P13: 805515 | Q13: Centralizada (ativo contratual testado como população única – base sintética)
A14: IESul | B14: Controlada | C14: F0270 | D14: Deloitte Touche Tohmatsu | E14: 31 de março de 2026 | F14: Sem modificação | G14: 264831 | H14: 5 | I14: 29933 | J14: 8431 | K14: 1 | L14: 8431 | M14: =ROUND(J14*K14-L14,0) -> 0 | N14: =G14/47201372 -> 0.0056106632 | O14: 189305 | P14: 253572 | Q14: Centralizada (ativo contratual testado como população única – base sintética)
A15: IE Biguaçu | B15: Controlada | C15: F0260 | D15: Deloitte Touche Tohmatsu | E15: 31 de março de 2026 | F15: Sem modificação | G15: 572807 | H15: 5 | I15: 69511 | J15: 56779 | K15: 1 | L15: 56779 | M15: =ROUND(J15*K15-L15,0) -> 0 | N15: =G15/47201372 -> 0.012135389 | O15: 496467 | P15: 554346 | Q15: Centralizada (ativo contratual testado como população única – base sintética)
... A19: IE Jaguar 9 | B19: Controlada | C19: F0274 | D19: Deloitte Touche Tohmatsu | E19: 31 de março de 2026 | F19: Sem modificação | G19: 619964 | H19: 5 | I19: 89329 | J19: 72914 | K19: 1 | L19: 72912 | M19: =ROUND(J19*K19-L19,0) -> 2 | N19: =G19/47201372 -> 0.013134449 | O19: 540502 | P19: 617083 | Q19: Centralizada (ativo contratual testado como população única – base sintética)
A20: IE Madeira | B20: Controlada em conjunto | C20: F0259 | D20: Deloitte Touche Tohmatsu | E20: 4 de fevereiro de 2026 | F20: Sem modificação | G20: 7225118 | H20: 10 | I20: 768933 | J20: 476992 | K20: 0.51 | L20: 243266 | M20: =ROUND(J20*K20-L20,0) -> 0 | N20: =G20/47201372 -> 0.15307008 | O20: 2293888 | P20: n/a (não consolidado) | Q20: Equivalência: recálculo da participação e leitura das DFs auditadas; comunicação do auditor do componente [PA]
A21: IE Garanhuns | B21: Controlada em conjunto | C21: F0258 | D21: Deloitte Touche Tohmatsu | E21: 10 de março de 2026 | F21: Sem modificação | G21: 1591405 | H21: 15 | I21: 178814 | J21: 137047 | K21: 0.51 | L21: 69894 | M21: =ROUND(J21*K21-L21,0) -> 0 | N21: =G21/47201372 -> 0.033715228 | O21: 603592 | P21: n/a (não consolidado) | Q21: Equivalência: recálculo da participação e leitura das DFs auditadas; comunicação do auditor do componente [PA]
A22: IE Paraguaçu | B22: Controlada em conjunto | C22: F0279 | D22: Deloitte Touche Tohmatsu | E22: 26 de março de 2026 | F22: Sem modificação | G22: 1756416 | H22: 7 | I22: 196714 | J22: 137698 | K22: 0.5 | L22: 68850 | M22: =ROUND(J22*K22-L22,0) -> -1 | N22: =G22/47201372 -> 0.037211122 | O22: 387609 | P22: n/a (não consolidado) | Q22: Equivalência: recálculo da participação e leitura das DFs auditadas; comunicação do auditor do componente [PA]
A23: IE Aimorés | B23: Controlada em conjunto | C23: F0278 | D23: Deloitte Touche Tohmatsu | E23: 26 de março de 2026 | F23: Sem modificação | G23: 1122605 | H23: 7 | I23: 130806 | J23: 92302 | K23: 0.5 | L23: 46151 | M23: =ROUND(J23*K23-L23,0) -> 0 | N23: =G23/47201372 -> 0.023783313 | O23: 258000 | P23: n/a (não consolidado) | Q23: Equivalência: recálculo da participação e leitura das DFs auditadas; comunicação do auditor do componente [PA]
A24: IE Ivaí | B24: Controlada em conjunto | C24: F0266 | D24: Deloitte Touche Tohmatsu | E24: 31 de março de 2026 | F24: Sem modificação | G24: 4656226 | H24: 5 | I24: 480217 | J24: 165778 | K24: 0.5 | L24: 82888 | M24: =ROUND(J24*K24-L24,0) -> 1 | N24: =G24/47201372 -> 0.098645989 | O24: 611726 | P24: n/a (não consolidado) | Q24: Equivalência: recálculo da participação e leitura das DFs auditadas; comunicação do auditor do componente [PA]
A26: Soma das controladas | G26: =SUM(G4:G19) -> 8474171 | J26: =SUM(J4:J19) -> 780058 | L26: =SUM(L4:L19) -> 780056 | M26: =SUM(M4:M19) -> 2 | N26: =SUM(N4:N19) -> 0.1795323 | O26: =SUM(O4:O19) -> 7264449 | P26: =SUM(P4:P19) -> 8179040
A27: Soma das controladas em conjunto | L27: =SUM(L20:L24) -> 511049 | M27: =SUM(M20:M24) -> 0 | O27: =SUM(O20:O24) -> 4154815
A28: Equivalência consolidada publicada (F0003 p.62) | L28: 511049 | M28: =L27-L28 -> 0 | N28: Diferença entre soma e publicado

Sheet Conferencias_consolidacao
A1: Conferências de consolidação com dados públicos (R$ mil) – procedimentos [RP]; não substituem o acesso ao pacote de consolidação
A2: Item | B2: Valor A | C2: Valor B | D2: Valor C | E2: Resultado (fórmula) | F2: Fonte / interpretação
A3: C1 Ativo da concessão: consolidado − controladora × soma das 16 controladas (DFs dos componentes) | B3: 36431298 | C3: 28252258 | D3: =Matriz_componentes!P26 -> 8179040 | E3: =B3-C3-D3 -> 0 | F3: F0003 p.45 (nota 5.3, inclui O&M); DFs F0260–F0276 (balanços). Diferença 0 = ativo de concessão das controladas sem ajuste de consolidação
A4: C2 Patrimônio líquido: consolidado = controladora + não controladores dos fundos | B4: 21437011 | C4: 21151467 | D4: 285544 | E4: =B4-C4-D4 -> 0 | F4: F0003 p.24 (P28, P29, P30) e p.40
A5: C3 Equivalência: controladas (lucro × 100%) − nota 7.2 | B5: =Matriz_componentes!J26 -> 780058 | C5: =Matriz_componentes!L26 -> 780056 | E5: =B5-C5 -> 2 | F5: Diferenças de arredondamento (R$ mil) entre DFs dos componentes e nota 7.2 (F0003 p.60)
A6: C4 Equivalência consolidada: soma das controladas em conjunto × publicado | B6: =Matriz_componentes!L27 -> 511049 | C6: 511049 | E6: =B6-C6 -> 0 | F6: F0003 p.61–62
A7: C5 Investimento consolidado = soma dos investimentos em controladas em conjunto | B7: 4154815 | C7: =Matriz_componentes!O27 -> 4154815 | E7: =B7-C7 -> 0 | F7: F0003 p.23 (A17) e p.61
A8: C6 Ativo total: controladora + soma das controladas − consolidado = eliminações e efeitos dos fundos (não divulgados) | B8: 45960743 | C8: =Matriz_componentes!G26 -> 8474171 | D8: 47201372 | E8: =B8+C8-D8 -> 7233542 | F8: F0003 p.23. Contém, entre outros, investimentos em controladas eliminados (7.264.449 = 11.419.264 − 4.154.815, nota 7.2) e saldos entre partes relacionadas. Composição exata: INDISPONÍVEL
A9: C6a Parte explicada: investimentos em controladas eliminados | B9: 7264449 | E9: =E8-B9 -> -30907 | F9: Resíduo = outros saldos eliminados/efeitos dos fundos – a explicar com o pacote de consolidação [PA]

Sheet Prestadores_402
A1: Organizações prestadoras de serviços e terceiros relevantes para a informação financeira (PT 402). D = identificado documentalmente; H = hipótese a verificar
A2: ID | B2: Prestador | C2: Serviço | D2: Natureza (D/H) | E2: Fonte (ID, página) | F2: Contas / afirmações afetadas | G2: É organização prestadora de serviços (NBC TA 402)? | H2: Relatório tipo 1/2 disponível? | I2: Controles complementares esperados na ISA | J2: Procedimentos alternativos (it. 12, 16) | K2: Risco ligado
A3: S1 | B3: Banco Bradesco (administrador) | C3: Administração do FI RF Ref. DI Bandeirantes (cota, carteira, custódia) | D3: D | E3: F0003 p.58 | F3: Aplicações financeiras e caixa (existência, avaliação); não controladores dos fundos | G3: Sim – administração/custódia de fundo afeta o registro (A1–A3) | H3: Não localizado em fonte pública (não obtido) | I3: Conciliação mensal cota × extrato; aprovação de movimentações; revisão do regulamento | J3: Confirmação do saldo de cotas e do valor da cota com o administrador [PA]; recálculo de rendimento com CDI [RP]; leitura das DFs auditadas do fundo (não disponíveis – P13) | K3: R10, R18
A4: S2 | B4: Banco Itaú-Unibanco (administrador) | C4: Administração do FI Xavantes RF Ref. DI | D4: D | E4: F0003 p.58 | F4: Idem S1 | G4: Sim | H4: Não localizado | I4: Idem | J4: Idem | K4: R10, R18
A5: S3 | B5: Banco Santander (administrador) | C5: Administração do FI Assis RF Ref. DI | D5: D | E5: F0003 p.58 | F5: Idem S1 | G5: Sim | H5: Não localizado | I5: Idem | J5: Idem | K5: R10, R18
A6: S4 | B6: Banco do Brasil (administrador) | C6: Administração do FI Barra Bonita RF Ref. DI LP | D6: D | E6: F0003 p.58 | F6: Idem S1 | G6: Sim | H6: Não localizado | I6: Idem | J6: Idem | K6: R10, R18
A7: S5 | B7: ONS – Operador Nacional do Sistema Elétrico | C7: Apuração e informação mensal do faturamento (AVC) dos usuários, parcela variável e administração de garantias | D7: D | E7: F0003 p.45 (nota 5.3(i)), p.47 | F7: Recebimentos e receita de O&M; contas a receber; perda esperada (ocorrência, exatidão, avaliação) | G7: Em parte: entidade regulada sem contrato de serviço com a ISA; suas apurações entram no sistema de informação da ISA (tratar por analogia, it. 9) | H7: Não existe relatório tipo 1/2 público conhecido | I7: Conferência dos AVC com a RAP homologada; acompanhamento de inadimplência e garantias | J7: Recálculo RAP × faturamento por contrato [RP/SD]; inspeção dos AVC [PA]; confirmação de saldos com usuários [PA] | K7: R02, R03, R04
A8: S6 | B8: Vivest (Fundação CESP) | C8: Administração dos planos de previdência e processamento da folha de complementação da Lei 4.819/58 (por determinação da SEFAZ desde dez/2017) | D8: D | E8: F0003 p.72, p.78, p.82 | F8: Recebível SEFAZ (R$ 2.760.806 mil); obrigações de benefício pós-emprego | G8: Sim para a folha e para a administração do plano (processa transações que afetam os registros) | H8: Não localizado | I8: Conciliação dos repasses à Vivest × valores recebidos da SEFAZ; revisão do relatório atuarial | J8: Confirmação com a Vivest dos repasses e saldos [PA]; leitura das notas 9 e 11 [RP]; avaliação do atuário como especialista da administração (NBC TA 500) [PA] | K8: R05
A9: S7 | B9: Atuário independente (não identificado nominalmente) | C9: Avaliação atuarial do PSAP e dos benefícios | D9: D (sem nome) | E9: F0003 p.79 | F9: Benefício pós-emprego; ORA | G9: Não: é especialista da administração (NBC TA 500), não organização prestadora de serviços | H9: — | I9: — | J9: PT 500/540: competência e objetividade do especialista; premissas [PA] | K9: R09
A10: S8 | B10: Taesa (sócia e administradora) | C10: Atividades administrativas e O&M de IE Aimorés e IE Paraguaçu (compartilhamento de infraestrutura e RH) | D10: D | E10: F0278 p.3 e p.22 (Aimorés); F0279 (Paraguaçu, mesma estrutura) | F10: Investimentos e equivalência (R08): as DFs das JVs são elaboradas sob administração da Taesa | G10: Para a ISA, é fonte da informação financeira da JV (via DFs auditadas), não prestadora contratada da ISA | H10: Não aplicável/não localizado | I10: Revisão pela ISA das informações das JVs antes da equivalência | J10: Leitura das DFs auditadas (Deloitte, 26/03/2026) [RP]; recálculo da equivalência [RP]; comunicação com o auditor do componente [PA] | K10: R08
A11: S9 | B11: ISA Energia Brasil (centro de serviços compartilhados) | C11: Presta às controladas serviços administrativos compartilhados, O&M, engenharia e gestão de obras | D11: D | E11: F0261 p.32 (nota de partes relacionadas da IE Aguapeí; mesma estrutura nas demais) | F11: Processos contábeis e de medição das controladas (centralizados) | G11: Não: serviço intragrupo – tratado no PT 600 como processo centralizado | H11: — | I11: — | J11: Testes centralizados no grupo (PT 600 §6.3) | K11: R01, R02, R19
A12: S10 | B12: Oliveira Trust | C12: Escriturador das 18ª e 19ª emissões de debêntures | D12: D | E12: F0059 e F0064 (atas da RCA 05/2025 e 10/2025) | F12: Debêntures (existência, titularidade) – efeito baixo no valor contábil | G12: Em parte: escrituração de títulos; baixo efeito nas DFs | H12: Não localizado | I12: Conciliação do saldo escritural × razão | J12: Confirmação com o escriturador/agente fiduciário [PA] | K12: R06
A13: S11 | B13: Provedor de sistemas/ERP, hospedagem ou nuvem | C13: Processamento contábil e de faturamento | D13: H | E13: FRE cita gastos com consultoria de TI (F0053); sistemas não descritos (P20) | F13: Todas as contas | G13: A verificar | H13: Desconhecido | I13: Controles gerais de TI (acesso, mudanças) | J13: Indagação e inspeção de contratos [PA] | K13: R16, todos
A14: S12 | B14: Processamento de folha de pagamento (ISA) | C14: Folha da companhia | D14: H | E14: Não identificado | F14: Despesas de pessoal; obrigações trabalhistas (baixa materialidade) | G14: A verificar | H14: Desconhecido | I14: — | J14: Indagação [PA]; analítico de pessoal [RP] | K14: —

Sheet Indisponiveis
A1: Informações indisponíveis e sua utilidade (não inventadas; tratadas como limitação ou procedimento [PA])
A2: Informação | B2: Utilidade para o trabalho | C2: Situação | D2: Pendência
A3: Pacote de consolidação (eliminações por natureza) | B3: Explicar o resíduo da conferência C6 e testar eliminações (PG-CONS) | C3: Não público | D3: P25
A4: Comunicações entre o auditor do grupo e os auditores dos componentes (instruções, relatórios, papéis) | B4: NBC TA 600 it. 29–32, 45–48 | C4: Não públicas; NÃO foram presumidas | D4: P25
A5: Pacotes de reporte dos componentes para o grupo (datados antes de 24/02/2026) | B5: Os relatórios estatutários dos componentes são de 31/03/2026 (posteriores ao relatório do grupo de 24/02/2026); o auditor do grupo usou outra evidência, não pública | C5: Não público | D5: P25
A6: Acordos de acionistas das JVs (íntegra) | B6: Confirmar cláusulas de controle conjunto (decisões unânimes) | C6: Não localizados; existência citada nas DFs das JVs (F0259 p.17; F0278; F0279) | D6: P26
A7: DFs e regulamentos dos 4 fundos exclusivos | B7: Confirmar controle, cotas e não controladores (R$ 285.544 mil) | C7: Não localizados | D7: P13
A8: Relatórios tipo 1/tipo 2 (ISAE 3402/NBC TO 3402) dos administradores dos fundos, da Vivest ou de provedores de TI | B8: NBC TA 402 it. 12–17 | C8: Não localizados em fonte pública; NÃO examinados | D8: P27
